dynamo/__init__.py
dynamo/configuration.py
dynamo/data_io.py
dynamo/docrep.py
dynamo/dynamo_logger.py
dynamo/est.py
dynamo/ext.py
dynamo/get_version.py
dynamo/mv.py
dynamo/pd.py
dynamo/pl.py
dynamo/pp.py
dynamo/sample_data.py
dynamo/shiny.py
dynamo/sim.py
dynamo/tl.py
dynamo/utils.py
dynamo/vf.py
dynamo/estimation/__init__.py
dynamo/estimation/deprecated.py
dynamo/estimation/fit_jacobian.py
dynamo/estimation/csc/__init__.py
dynamo/estimation/csc/utils_velocity.py
dynamo/estimation/csc/velocity.py
dynamo/estimation/tsc/ODEs.py
dynamo/estimation/tsc/__init__.py
dynamo/estimation/tsc/estimation_kinetic.py
dynamo/estimation/tsc/twostep.py
dynamo/estimation/tsc/utils_moments.py
dynamo/external/__init__.py
dynamo/external/gseapy.py
dynamo/external/hodge.py
dynamo/external/scifate.py
dynamo/external/scribe.py
dynamo/external/utils.py
dynamo/movie/__init__.py
dynamo/movie/fate.py
dynamo/movie/utils.py
dynamo/plot/__init__.py
dynamo/plot/cell_cycle.py
dynamo/plot/clustering.py
dynamo/plot/connectivity.py
dynamo/plot/dimension_reduction.py
dynamo/plot/dynamics.py
dynamo/plot/ezplots.py
dynamo/plot/fate.py
dynamo/plot/fate_utilities_deprecated.py
dynamo/plot/heatmaps.py
dynamo/plot/least_action_path.py
dynamo/plot/markers.py
dynamo/plot/networks.py
dynamo/plot/preprocess.py
dynamo/plot/pseudotime.py
dynamo/plot/scPotential.py
dynamo/plot/scVectorField.py
dynamo/plot/scatters.py
dynamo/plot/sctransform.py
dynamo/plot/space.py
dynamo/plot/state_graph.py
dynamo/plot/streamtube.py
dynamo/plot/theme.py
dynamo/plot/time_series.py
dynamo/plot/topography.py
dynamo/plot/utils.py
dynamo/plot/utils_dynamics.py
dynamo/plot/utils_graph.py
dynamo/plot/vector_calculus.py
dynamo/prediction/__init__.py
dynamo/prediction/fate.py
dynamo/prediction/least_action_path.py
dynamo/prediction/perturbation.py
dynamo/prediction/state_graph.py
dynamo/prediction/trajectory.py
dynamo/prediction/trajectory_analysis.py
dynamo/prediction/tscRNA_seq.py
dynamo/prediction/utils.py
dynamo_release-1.4.1.dist-info/LICENSE
dynamo_release-1.4.1.dist-info/METADATA
dynamo_release-1.4.1.dist-info/WHEEL
dynamo_release-1.4.1.dist-info/top_level.txt
dynamo_release-1.4.1.dist-info/RECORD
