Metadata-Version: 2.1
Name: dynamo-release
Version: 1.4.1
Summary: Mapping Vector Field of Single Cells
Home-page: https://github.com/aristoteleo/dynamo-release
Author: Xiaojie Qiu, Yan Zhang, Ke Ni
Author-email: xqiu.sc@gmail.com
License: BSD
Download-URL: https://github.com/aristoteleo/dynamo-release
Keywords: VectorField,singlecell,velocity,scNT-seq,sci-fate,NASC-seq,scSLAMseq,potential
Platform: UNKNOWN
Classifier: Programming Language :: Python :: 3
Classifier: License :: OSI Approved :: BSD License
Classifier: Operating System :: OS Independent
Requires-Python: >=3.7
Requires-Dist: numpy <2.0.0,>=1.20.0
Requires-Dist: pandas >=1.3.5
Requires-Dist: scipy >=1.4.1
Requires-Dist: scikit-learn <1.5.0,>=0.19.1
Requires-Dist: anndata >=0.8.0
Requires-Dist: loompy >=3.0.5
Requires-Dist: matplotlib >=3.7.5
Requires-Dist: setuptools
Requires-Dist: numdifftools >=0.9.39
Requires-Dist: umap-learn >=0.5.1
Requires-Dist: PATSY >=0.5.1
Requires-Dist: statsmodels >=0.9.0
Requires-Dist: numba >=0.54.0
Requires-Dist: seaborn >=0.9.0
Requires-Dist: colorcet >=2.0.1
Requires-Dist: tqdm
Requires-Dist: igraph >=0.7.1
Requires-Dist: leidenalg
Requires-Dist: pynndescent >=0.5.2
Requires-Dist: pre-commit
Requires-Dist: networkx >=2.6
Requires-Dist: get-version >=3.5.4
Requires-Dist: openpyxl
Requires-Dist: typing-extensions
Requires-Dist: session-info >=1.0.0
Provides-Extra: docs
Requires-Dist: sphinx >=4.0.2 ; extra == 'docs'
Requires-Dist: sphinx-rtd-theme >=0.5.1 ; extra == 'docs'
Requires-Dist: sphinx-autodoc-typehints ; extra == 'docs'
Requires-Dist: ipykernel >=5.1.0 ; extra == 'docs'
Requires-Dist: nbsphinx ==0.8.11 ; extra == 'docs'
Requires-Dist: pygments >=2.6.1 ; extra == 'docs'
Requires-Dist: numpy >=1.18.1 ; extra == 'docs'
Requires-Dist: pandas >=1.3.5 ; extra == 'docs'
Requires-Dist: scipy >=1.0 ; extra == 'docs'
Requires-Dist: scikit-learn >=0.19.1 ; extra == 'docs'
Requires-Dist: cvxopt >=1.2.3 ; extra == 'docs'
Requires-Dist: anndata >=0.8.0 ; extra == 'docs'
Requires-Dist: loompy >=3.0.5 ; extra == 'docs'
Requires-Dist: matplotlib >=3.5.3 ; extra == 'docs'
Requires-Dist: trimap >=1.0.11 ; extra == 'docs'
Requires-Dist: setuptools ; extra == 'docs'
Requires-Dist: numdifftools >=0.9.39 ; extra == 'docs'
Requires-Dist: umap-learn >=0.5.1 ; extra == 'docs'
Requires-Dist: PATSY >=0.5.1 ; extra == 'docs'
Requires-Dist: statsmodels >=0.9.0 ; extra == 'docs'
Requires-Dist: numba >=0.46.0 ; extra == 'docs'
Requires-Dist: seaborn >=0.9.0 ; extra == 'docs'
Requires-Dist: colorcet >=2.0.1 ; extra == 'docs'
Requires-Dist: tqdm ; extra == 'docs'
Requires-Dist: igraph >=0.7.1 ; extra == 'docs'
Requires-Dist: pynndescent >=0.5.2 ; extra == 'docs'
Requires-Dist: gseapy ; extra == 'docs'
Requires-Dist: GitPython ; extra == 'docs'
Requires-Dist: KDEpy ; extra == 'docs'
Requires-Dist: docutils ; extra == 'docs'
Requires-Dist: mock ; extra == 'docs'
Requires-Dist: pandocfilters ; extra == 'docs'
Requires-Dist: readthedocs-sphinx-ext ; extra == 'docs'
Requires-Dist: sphinxcontrib-bibtex >=2.3 ; extra == 'docs'
Requires-Dist: sphinx-gallery ; extra == 'docs'
Requires-Dist: typing-extensions ; extra == 'docs'
